{
  "_fv": 6,
  "_type": "gui",
  "definition": {
    "type": 0,
    "width": 854,
    "height": 480,
    "renderBgLayer": false,
    "components": [
      {
        "type": "button",
        "data": {
          "text": "Era 1 before Pink Diamond",
          "width": 500,
          "height": 40,
          "name": "Era 1 before Pink Diamond",
          "x": 12,
          "y": 24
        }
      },
      {
        "type": "button",
        "data": {
          "text": "Era 1",
          "width": 100,
          "height": 40,
          "name": "Era 1",
          "x": 552,
          "y": 24
        }
      },
      {
        "type": "button",
        "data": {
          "text": "Era 2 pre-war",
          "width": 260,
          "height": 40,
          "name": "Era 2 pre-war",
          "x": 12,
          "y": 96
        }
      },
      {
        "type": "button",
        "data": {
          "text": "Era 2 war",
          "width": 180,
          "height": 40,
          "name": "Era 2 war",
          "x": 300,
          "y": 96
        }
      },
      {
        "type": "button",
        "data": {
          "text": "Era 2 post-war",
          "width": 280,
          "height": 40,
          "name": "Era 2 post-war",
          "x": 516,
          "y": 96
        }
      },
      {
        "type": "button",
        "data": {
          "text": "Era 3",
          "width": 100,
          "height": 40,
          "name": "Era 3",
          "x": 12,
          "y": 168
        }
      },
      {
        "type": "button",
        "data": {
          "text": "Other",
          "width": 100,
          "height": 40,
          "name": "Other",
          "x": 138,
          "y": 168
        }
      },
      {
        "type": "label",
        "data": {
          "text": "Decide on when your journey takes place",
          "color": {
            "value": -1,
            "falpha": 0.0
          },
          "name": "Decide on when your journey takes place",
          "x": 264,
          "y": 384
        }
      },
      {
        "type": "button",
        "data": {
          "text": "Help",
          "width": 80,
          "height": 40,
          "name": "Help",
          "x": 390,
          "y": 312
        }
      }
    ]
  }
}